MANIFEST.in
README.md
README.rst
setup.cfg
setup.py
gtom/__init__.py
gtom/gtom_calculator.py
gtom/gtom_funcs.py
gtom.egg-info/PKG-INFO
gtom.egg-info/SOURCES.txt
gtom.egg-info/dependency_links.txt
gtom.egg-info/not-zip-safe
gtom.egg-info/requires.txt
gtom.egg-info/top_level.txt