Metadata-Version: 1.1
Name: gtom
Version: 0.5
Summary: computes the general topological overlap matrix of an undirected network
Home-page: https://github.com/benmaier/gtom
Author: Benjamin Maier
Author-email: bfmaier@physik.hu-berlin.de
License: MIT
Platform: UNKNOWN
Classifier: Programming Language :: Python :: 2.7
Classifier: Programming Language :: Python :: 3
